rph/__init__.py
rph/rph.py
rph-1.0.0.dist-info/LICENSE
rph-1.0.0.dist-info/METADATA
rph-1.0.0.dist-info/WHEEL
rph-1.0.0.dist-info/top_level.txt
rph-1.0.0.dist-info/RECORD
