Metadata-Version: 2.1
Name: rph
Version: 1.0.0
Summary: PyTorch module for random projection hashing
Home-page: https://github.com/ag14774/rph.git
Author: Andreas Georgiou
Author-email: geandrea@ethz.ch
License: UNKNOWN
Platform: UNKNOWN
Classifier: Programming Language :: Python :: 3
Classifier: License :: OSI Approved :: MIT License
Classifier: Operating System :: OS Independent
Classifier: Topic :: Scientific/Engineering :: Artificial Intelligence
Requires-Python: >=3.6
